MANIFEST.in
README.rst
setup.cfg
setup.py
versioneer.py
hizzard/__init__.py
hizzard/_version.py
hizzard/core.py
hizzard.egg-info/PKG-INFO
hizzard.egg-info/SOURCES.txt
hizzard.egg-info/dependency_links.txt
hizzard.egg-info/requires.txt
hizzard.egg-info/top_level.txt