Metadata-Version: 1.1
Name: hizzard
Version: 0.0.9
Summary: Great package.
Home-page: https://github.com/shaypal5/ezenum
Author: Shay Palachy
Author-email: shaypal5@gmail.com
License: MIT
Keywords: enum
Platform: any
Classifier: Development Status :: 4 - Beta
Classifier: License :: OSI Approved :: MIT License
Classifier: Programming Language :: Python
Classifier: Programming Language :: Python :: 3.5
Classifier: Programming Language :: Python :: 3.6
Classifier: Topic :: Software Development :: Libraries
Classifier: Topic :: Software Development :: Libraries :: Python Modules
Classifier: Intended Audience :: Developers
